onionGpio.py
onion_gpio_sysfs-0.1.6.dist-info/LICENSE.md
onion_gpio_sysfs-0.1.6.dist-info/METADATA
onion_gpio_sysfs-0.1.6.dist-info/WHEEL
onion_gpio_sysfs-0.1.6.dist-info/top_level.txt
onion_gpio_sysfs-0.1.6.dist-info/RECORD
