Metadata-Version: 2.1
Name: onion-gpio-sysfs
Version: 0.1.6
Summary: Libraries to control GPIOs using the sysfs interface
Home-page: https://github.com/grizmin/onion-gpio-sysfs
Author: Grizmin
Author-email: grizmin@gmail.com
License: UNKNOWN
Keywords: onion omega IoT
Platform: UNKNOWN
Classifier: Programming Language :: Python :: 3
Classifier: License :: OSI Approved :: GNU General Public License v3 (GPLv3)
Classifier: Operating System :: POSIX :: Linux
Classifier: Programming Language :: Python :: 2
Classifier: Programming Language :: Python :: 2.7
Classifier: Programming Language :: Python :: 3
Classifier: Programming Language :: Python :: 3.5
Classifier: Programming Language :: Python :: 3.6
Classifier: Programming Language :: Python :: 3.7
Classifier: Programming Language :: Python :: 3.8
Requires-Python: >=2.7, !=3.0.*, !=3.1.*, !=3.2.*, !=3.3.*, !=3.4.*, <4
